easyapiopenai/__init__.py
easyapiopenai/apiwojopenai.py
EasyAPIOpenAI-0.1.2.dist-info/LICENSE
EasyAPIOpenAI-0.1.2.dist-info/METADATA
EasyAPIOpenAI-0.1.2.dist-info/WHEEL
EasyAPIOpenAI-0.1.2.dist-info/top_level.txt
EasyAPIOpenAI-0.1.2.dist-info/RECORD
