Metadata-Version: 2.1
Name: EasyAPIOpenAI
Version: 0.1.2
Summary: Python classes for interacting with OpenAI's API to use ChatGPT or DALL-E very easily.
Home-page: https://github.com/Wojtekb30/EasyAPIOpenAI
Author: Wojtekb30 (Wojciech B)
Author-email: wojtekb30.player@gmail.com
Classifier: Programming Language :: Python :: 3
Classifier: License :: OSI Approved :: MIT License
Classifier: Operating System :: OS Independent
Requires-Python: >=3.6
License-File: LICENSE
Requires-Dist: requests >=2.20.0
Requires-Dist: pillow >=8.0.0
